MANIFEST.in
setup.py
sphinx_boost/__init__.py
sphinx_boost.egg-info/PKG-INFO
sphinx_boost.egg-info/SOURCES.txt
sphinx_boost.egg-info/dependency_links.txt
sphinx_boost.egg-info/not-zip-safe
sphinx_boost.egg-info/top_level.txt
sphinx_boost/boost/layout.html
sphinx_boost/boost/theme.conf
sphinx_boost/boost/static/alert.png
sphinx_boost/boost/static/blank.png
sphinx_boost/boost/static/boost-proposed.png
sphinx_boost/boost/static/boost.png
sphinx_boost/boost/static/boostbook.css
sphinx_boost/boost/static/caution.png
sphinx_boost/boost/static/caution.svg
sphinx_boost/boost/static/draft.png
sphinx_boost/boost/static/home.png
sphinx_boost/boost/static/home.svg
sphinx_boost/boost/static/important.png
sphinx_boost/boost/static/important.svg
sphinx_boost/boost/static/next.png
sphinx_boost/boost/static/next.svg
sphinx_boost/boost/static/next_disabled.png
sphinx_boost/boost/static/note.png
sphinx_boost/boost/static/note.svg
sphinx_boost/boost/static/prev.png
sphinx_boost/boost/static/prev.svg
sphinx_boost/boost/static/prev_disabled.png
sphinx_boost/boost/static/smiley.png
sphinx_boost/boost/static/tip.png
sphinx_boost/boost/static/tip.svg
sphinx_boost/boost/static/toc-blank.png
sphinx_boost/boost/static/toc-minus.png
sphinx_boost/boost/static/toc-plus.png
sphinx_boost/boost/static/up.png
sphinx_boost/boost/static/up.svg
sphinx_boost/boost/static/up_disabled.png
sphinx_boost/boost/static/warning.png
sphinx_boost/boost/static/warning.svg
sphinx_boost/boost/static/callouts/1.png
sphinx_boost/boost/static/callouts/1.svg
sphinx_boost/boost/static/callouts/10.png
sphinx_boost/boost/static/callouts/10.svg
sphinx_boost/boost/static/callouts/11.png
sphinx_boost/boost/static/callouts/11.svg
sphinx_boost/boost/static/callouts/12.png
sphinx_boost/boost/static/callouts/12.svg
sphinx_boost/boost/static/callouts/13.png
sphinx_boost/boost/static/callouts/13.svg
sphinx_boost/boost/static/callouts/14.png
sphinx_boost/boost/static/callouts/14.svg
sphinx_boost/boost/static/callouts/15.png
sphinx_boost/boost/static/callouts/15.svg
sphinx_boost/boost/static/callouts/16.svg
sphinx_boost/boost/static/callouts/17.svg
sphinx_boost/boost/static/callouts/18.svg
