Metadata-Version: 1.0
Name: sphinx-boost
Version: 0.0.3
Summary: Boost theme for sphinx
Home-page: https://github.com/pfultz2/sphinx-boost
Author: Paul Fultz II
Author-email: pfultz2@yahoo.com
License: boost
Platform: UNKNOWN
